Metadata-Version: 1.1
Name: gitfiles-ctx
Version: 0.1.post6
Summary: Context manager for a file-based view on a remote Git repository.
Home-page: https://github.com/clearclaw/gitfiles_ctx
Author: J C Lawrence
Author-email: claw@kanga.nu
License: LGPL v3.0
Keywords: git,view,context
Platform: UNKNOWN
Classifier: Development Status :: 4 - Beta
Classifier: Intended Audience :: Developers
Classifier: License :: OSI Approved :: GNU Lesser General Public License v3 or later (LGPLv3+)
Classifier: Topic :: Utilities
